atitd/__init__.py
atitd/cli.py
atitd-0.0.2.dist-info/DESCRIPTION.rst
atitd-0.0.2.dist-info/METADATA
atitd-0.0.2.dist-info/RECORD
atitd-0.0.2.dist-info/WHEEL
atitd-0.0.2.dist-info/entry_points.txt
atitd-0.0.2.dist-info/metadata.json
atitd-0.0.2.dist-info/top_level.txt
tests/__init__.py
tests/test_cli.py
