Metadata-Version: 2.0
Name: atitd
Version: 0.0.2
Summary: Python automation tools for A Tale In The Desert (ATITD)
Home-page: https://github.com/levi-rs/atitd
Author: Levi Noecker
Author-email: levi.noecker@gmail.com
License: UNKNOWN
Platform: UNKNOWN
Requires-Dist: click
